.DS_Store
tedsverysimplemodule8807/__init__.py
tedsverysimplemodule8807/add.py
tedsverysimplemodule8807/subtract.py
tedsverysimplemodule8807/extras/__init__.py
tedsverysimplemodule8807/extras/divide.py
tedsverysimplemodule8807/extras/multiply.py
tedsverysimplemodule8807-0.0.2.dist-info/METADATA
tedsverysimplemodule8807-0.0.2.dist-info/WHEEL
tedsverysimplemodule8807-0.0.2.dist-info/top_level.txt
tedsverysimplemodule8807-0.0.2.dist-info/RECORD
